LICENSE-MIT
MANIFEST.in
README.rst
setup.py
exsort/__init__.py
exsort/sorting.py
exsort.egg-info/PKG-INFO
exsort.egg-info/SOURCES.txt
exsort.egg-info/dependency_links.txt
exsort.egg-info/top_level.txt
tests/__init__.py
tests/test_exsort.py