Metadata-Version: 1.1
Name: exsort
Version: 0.0.1
Summary: UNKNOWN
Home-page: https://github.com/andyhorng/exsort
Author: Andy Hung
Author-email: andyhorng168@gmail.com
License: MIT
Download-URL: https://github.com/andyhorng/exsort/archive/0.1.tar.gz
Keywords: external sorting,sorting,utility
Platform: UNKNOWN
Classifier: Development Status :: 4 - Beta
Classifier: Intended Audience :: Developers
Classifier: License :: OSI Approved :: MIT License
Classifier: Natural Language :: English
Classifier: Operating System :: OS Independent
Classifier: Programming Language :: Python :: 2.7
Classifier: Programming Language :: Python :: 3.5
Classifier: Programming Language :: Python :: 3.6
Classifier: Programming Language :: Python :: Implementation :: CPython
Classifier: Programming Language :: Python :: Implementation :: PyPy
